CHANGES.txt
COPYRIGHT.txt
LICENSE.txt
MANIFEST.in
README.txt
bootstrap.py
buildout.cfg
setup.py
bin/buildout
bin/test
src/tranchitella/__init__.py
src/tranchitella.recipe.nose.egg-info/PKG-INFO
src/tranchitella.recipe.nose.egg-info/SOURCES.txt
src/tranchitella.recipe.nose.egg-info/dependency_links.txt
src/tranchitella.recipe.nose.egg-info/entry_points.txt
src/tranchitella.recipe.nose.egg-info/namespace_packages.txt
src/tranchitella.recipe.nose.egg-info/not-zip-safe
src/tranchitella.recipe.nose.egg-info/requires.txt
src/tranchitella.recipe.nose.egg-info/top_level.txt
src/tranchitella/recipe/__init__.py
src/tranchitella/recipe/nose/__init__.py
src/tranchitella/recipe/nose/recipe.txt
src/tranchitella/recipe/nose/tests.py