Metadata-Version: 1.0
Name: tranchitella.recipe.nose
Version: 0.1
Summary: Buildout recipe to create a nose test runner
Home-page: http://pypi.python.org/pypi/tranchitella.recipe.nose
Author: Tranchitella Kft.
Author-email: info@tranchitella.eu
License: GPL 2
Platform: UNKNOWN
Classifier: Framework :: Buildout
Classifier: Intended Audience :: Developers
Classifier: Intended Audience :: System Administrators
Classifier: License :: OSI Approved :: GNU General Public License (GPL)
Classifier: Programming Language :: Python
